<?xml version="1.0" encoding="UTF-8"?><ent name="eventplugin"><par name="launchFlag_m" type="1"><val>1</val></par><par name="pluginClass_m" type="8"><val>com.fin.httrader.eventplugins.HtMutualIndexMove</val></par><xmlparlist name="initParams_m"><ent name=""><par name="java_key_type" type="8"><val>java.lang.String</val></par><par name="java_value_type" type="8"><val>java.lang.String</val></par><xmlpar name="value"><ent name=""><par name="value" type="8"><val>c:\work\German_work\in\modules.txt</val></par></ent></xmlpar><xmlpar name="key"><ent name=""><par name="value" type="8"><val>SYMBOL_FILE</val></par></ent></xmlpar></ent><ent name=""><par name="java_key_type" type="8"><val>java.lang.String</val></par><par name="java_value_type" type="8"><val>java.lang.String</val></par><xmlpar name="value"><ent name=""><par name="value" type="8"><val>localhost</val></par></ent></xmlpar><xmlpar name="key"><ent name=""><par name="value" type="8"><val>DB_HOST</val></par></ent></xmlpar></ent><ent name=""><par name="java_key_type" type="8"><val>java.lang.String</val></par><par name="java_value_type" type="8"><val>java.lang.String</val></par><xmlpar name="value"><ent name=""><par name="value" type="8"><val>3306</val></par></ent></xmlpar><xmlpar name="key"><ent name=""><par name="value" type="8"><val>DB_PORT</val></par></ent></xmlpar></ent><ent name=""><par name="java_key_type" type="8"><val>java.lang.String</val></par><par name="java_value_type" type="8"><val>java.lang.String</val></par><xmlpar name="value"><ent name=""><par name="value" type="8"><val>root</val></par></ent></xmlpar><xmlpar name="key"><ent name=""><par name="value" type="8"><val>DB_USER</val></par></ent></xmlpar></ent><ent name=""><par name="java_key_type" type="8"><val>java.lang.String</val></par><par name="java_value_type" type="8"><val>java.lang.String</val></par><xmlpar name="value"><ent name=""><par name="value" type="8"><val>admin</val></par></ent></xmlpar><xmlpar name="key"><ent name=""><par name="value" type="8"><val>DB_PASSWORD</val></par></ent></xmlpar></ent><ent name=""><par name="java_key_type" type="8"><val>java.lang.String</val></par><par name="java_value_type" type="8"><val>java.lang.String</val></par><xmlpar name="value"><ent name=""><par name="value" type="8"><val>htrader_gate</val></par></ent></xmlpar><xmlpar name="key"><ent name=""><par name="value" type="8"><val>DB_DATABASE</val></par></ent></xmlpar></ent></xmlparlist></ent>